examples/listings.py
examples/orders.py
examples/search.py
stockx/__init__.py
stockx/connection.py
stockx/listings.py
stockx/orders.py
stockx/search.py
stockx/secure.py
stockx/test.py
stockx-1.1.1.dist-info/licenses/LICENSE
stockx-1.1.1.dist-info/METADATA
stockx-1.1.1.dist-info/WHEEL
stockx-1.1.1.dist-info/top_level.txt
stockx-1.1.1.dist-info/RECORD
