Metadata-Version: 2.4
Name: stockx
Version: 1.1.1
Summary: A Python SDK for seamless interaction with the StockX marketplace API
Author-email: Nick <njames.programming@gmail.com>
License-Expression: MIT
Project-URL: Homepage, https://github.com/RoyalGr4pe/stockx-sdk
Project-URL: Issues, https://github.com/RoyalGr4pe/stockx-sdk/issues
Classifier: Programming Language :: Python :: 3
Classifier: Operating System :: OS Independent
Requires-Python: >=3.9
License-File: LICENSE
Dynamic: license-file
